[
  {
    "t": "p",
    "v": [
      {
        "t": "v",
        "n": 1,
        "v": ""
      },
      {
        "t": "w",
        "v": "I"
      },
      {
        "t": "w",
        "v": "want"
      },
      {
        "t": "w",
        "v": "you"
      },
      {
        "t": "w",
        "v": "to"
      },
      {
        "t": "w",
        "v": "remember"
      },
      {
        "t": "w",
        "v": "brothers"
      },
      {
        "t": "w",
        "v": "and"
      },
      {
        "t": "w",
        "v": "sisters"
      },
      {
        "t": "w",
        "v": "that"
      },
      {
        "t": "w",
        "v": "our"
      },
      {
        "t": "w",
        "v": "Jewish"
      },
      {
        "t": "w",
        "v": "ancestors"
      },
      {
        "t": "w",
        "v": "were"
      },
      {
        "t": "w",
        "v": "following"
      },
      {
        "t": "w",
        "v": "God"
      },
      {
        "t": "w",
        "v": "who"
      },
      {
        "t": "w",
        "v": "led"
      },
      {
        "t": "w",
        "v": "them"
      },
      {
        "t": "w",
        "v": "out"
      },
      {
        "t": "w",
        "v": "of"
      },
      {
        "t": "w",
        "v": "Egypt"
      },
      {
        "t": "w",
        "v": "by"
      },
      {
        "t": "w",
        "v": "means"
      },
      {
        "t": "w",
        "v": "of"
      },
      {
        "t": "w",
        "v": "a"
      },
      {
        "t": "w",
        "v": "cloud"
      },
      {
        "t": "w",
        "v": "during"
      },
      {
        "t": "w",
        "v": "the"
      },
      {
        "t": "w",
        "v": "day"
      },
      {
        "t": "w",
        "v": "and"
      },
      {
        "t": "w",
        "v": "that"
      },
      {
        "t": "w",
        "v": "they"
      },
      {
        "t": "w",
        "v": "passed"
      },
      {
        "t": "w",
        "v": "through"
      },
      {
        "t": "w",
        "v": "the"
      },
      {
        "t": "w",
        "v": "Sea"
      },
      {
        "t": "w",
        "v": "of"
      },
      {
        "t": "w",
        "v": "Reeds"
      },
      {
        "t": "w",
        "v": "on"
      },
      {
        "t": "w",
        "v": "dry"
      },
      {
        "t": "w",
        "v": "land"
      },
      {
        "t": "v",
        "n": 2,
        "v": ""
      },
      {
        "t": "w",
        "v": "And"
      },
      {
        "t": "w",
        "v": "as"
      },
      {
        "t": "w",
        "v": "we"
      },
      {
        "t": "w",
        "v": "have"
      },
      {
        "t": "w",
        "v": "been"
      },
      {
        "t": "w",
        "v": "baptized"
      },
      {
        "t": "w",
        "v": "into"
      },
      {
        "t": "w",
        "v": "the"
      },
      {
        "t": "w",
        "v": "Messiah"
      },
      {
        "t": "w",
        "v": "so"
      },
      {
        "t": "w",
        "v": "the"
      },
      {
        "t": "w",
        "v": "Israelites"
      },
      {
        "t": "w",
        "v": "were"
      },
      {
        "t": "w",
        "v": "to"
      },
      {
        "t": "w",
        "v": "follow"
      },
      {
        "t": "w",
        "v": "Moses"
      },
      {
        "t": "w",
        "v": "as"
      },
      {
        "t": "w",
        "v": "he"
      },
      {
        "t": "w",
        "v": "followed"
      },
      {
        "t": "w",
        "v": "God"
      },
      {
        "t": "w",
        "v": "in"
      },
      {
        "t": "w",
        "v": "the"
      },
      {
        "t": "w",
        "v": "cloud"
      },
      {
        "t": "w",
        "v": "and"
      },
      {
        "t": "w",
        "v": "across"
      },
      {
        "t": "w",
        "v": "the"
      },
      {
        "t": "w",
        "v": "sea"
      },
      {
        "t": "v",
        "n": 3,
        "v": ""
      },
      {
        "t": "w",
        "v": "They"
      },
      {
        "t": "w",
        "v": "all"
      },
      {
        "t": "w",
        "v": "ate"
      },
      {
        "t": "w",
        "v": "the"
      },
      {
        "t": "w",
        "v": "supernatural"
      },
      {
        "t": "w",
        "v": "manna"
      },
      {
        "t": "w",
        "v": "that"
      },
      {
        "t": "w",
        "v": "God"
      },
      {
        "t": "w",
        "v": "gave"
      },
      {
        "t": "w",
        "v": "them"
      },
      {
        "t": "w",
        "v": "from"
      },
      {
        "t": "w",
        "v": "heaven"
      },
      {
        "t": "v",
        "n": 4,
        "v": ""
      },
      {
        "t": "w",
        "v": "and"
      },
      {
        "t": "w",
        "v": "they"
      },
      {
        "t": "w",
        "v": "all"
      },
      {
        "t": "w",
        "v": "drank"
      },
      {
        "t": "w",
        "v": "the"
      },
      {
        "t": "w",
        "v": "supernatural"
      },
      {
        "t": "w",
        "v": "water"
      },
      {
        "t": "w",
        "v": "that"
      },
      {
        "t": "w",
        "v": "God"
      },
      {
        "t": "w",
        "v": "gave"
      },
      {
        "t": "w",
        "v": "them"
      },
      {
        "t": "w",
        "v": "when"
      },
      {
        "t": "w",
        "v": "Moses"
      },
      {
        "t": "w",
        "v": "struck"
      },
      {
        "t": "w",
        "v": "the"
      },
      {
        "t": "w",
        "v": "rock"
      },
      {
        "t": "w",
        "v": "The"
      },
      {
        "t": "w",
        "v": "rock"
      },
      {
        "t": "w",
        "v": "was"
      },
      {
        "t": "w",
        "v": "the"
      },
      {
        "t": "w",
        "v": "Messiah"
      },
      {
        "t": "v",
        "n": 5,
        "v": ""
      },
      {
        "t": "w",
        "v": "But"
      },
      {
        "t": "w",
        "v": "God"
      },
      {
        "t": "w",
        "v": "was"
      },
      {
        "t": "w",
        "v": "angry"
      },
      {
        "t": "w",
        "v": "with"
      },
      {
        "t": "w",
        "v": "most"
      },
      {
        "t": "w",
        "v": "of"
      },
      {
        "t": "w",
        "v": "them"
      },
      {
        "t": "w",
        "v": "because"
      },
      {
        "t": "w",
        "v": "they"
      },
      {
        "t": "w",
        "v": "worshiped"
      },
      {
        "t": "w",
        "v": "other"
      },
      {
        "t": "w",
        "v": "gods"
      },
      {
        "t": "w",
        "v": "and"
      },
      {
        "t": "w",
        "v": "rebelled"
      },
      {
        "t": "w",
        "v": "against"
      },
      {
        "t": "w",
        "v": "him"
      },
      {
        "t": "w",
        "v": "so"
      },
      {
        "t": "w",
        "v": "their"
      },
      {
        "t": "w",
        "v": "dead"
      },
      {
        "t": "w",
        "v": "bodies"
      },
      {
        "t": "w",
        "v": "lay"
      },
      {
        "t": "w",
        "v": "on"
      },
      {
        "t": "w",
        "v": "the"
      },
      {
        "t": "w",
        "v": "ground"
      },
      {
        "t": "w",
        "v": "all"
      },
      {
        "t": "w",
        "v": "across"
      },
      {
        "t": "w",
        "v": "the"
      },
      {
        "t": "w",
        "v": "wilderness"
      }
    ]
  },
  {
    "t": "p",
    "v": [
      {
        "t": "v",
        "n": 6,
        "v": ""
      },
      {
        "t": "w",
        "v": "Now"
      },
      {
        "t": "w",
        "v": "these"
      },
      {
        "t": "w",
        "v": "things"
      },
      {
        "t": "w",
        "v": "were"
      },
      {
        "t": "w",
        "v": "an"
      },
      {
        "t": "w",
        "v": "example"
      },
      {
        "t": "w",
        "v": "for"
      },
      {
        "t": "w",
        "v": "us"
      },
      {
        "t": "w",
        "v": "so"
      },
      {
        "t": "w",
        "v": "we"
      },
      {
        "t": "w",
        "v": "would"
      },
      {
        "t": "w",
        "v": "learn"
      },
      {
        "t": "w",
        "v": "not"
      },
      {
        "t": "w",
        "v": "to"
      },
      {
        "t": "w",
        "v": "greatly"
      },
      {
        "t": "w",
        "v": "desire"
      },
      {
        "t": "w",
        "v": "evil"
      },
      {
        "t": "w",
        "v": "things"
      },
      {
        "t": "w",
        "v": "as"
      },
      {
        "t": "w",
        "v": "they"
      },
      {
        "t": "w",
        "v": "did"
      },
      {
        "t": "v",
        "n": 7,
        "v": ""
      },
      {
        "t": "w",
        "v": "Some"
      },
      {
        "t": "w",
        "v": "of"
      },
      {
        "t": "w",
        "v": "our"
      },
      {
        "t": "w",
        "v": "ancestors"
      },
      {
        "t": "w",
        "v": "also"
      },
      {
        "t": "w",
        "v": "worshiped"
      },
      {
        "t": "w",
        "v": "idols"
      },
      {
        "t": "w",
        "v": "As"
      },
      {
        "t": "w",
        "v": "the"
      },
      {
        "t": "w",
        "v": "scripture"
      },
      {
        "t": "w",
        "v": "says"
      },
      {
        "t": "w",
        "v": "The"
      },
      {
        "t": "w",
        "v": "people"
      },
      {
        "t": "w",
        "v": "sat"
      },
      {
        "t": "w",
        "v": "down"
      },
      {
        "t": "w",
        "v": "to"
      },
      {
        "t": "w",
        "v": "eat"
      },
      {
        "t": "w",
        "v": "and"
      },
      {
        "t": "w",
        "v": "drink"
      },
      {
        "t": "w",
        "v": "and"
      },
      {
        "t": "w",
        "v": "then"
      },
      {
        "t": "w",
        "v": "they"
      },
      {
        "t": "w",
        "v": "rose"
      },
      {
        "t": "w",
        "v": "up"
      },
      {
        "t": "w",
        "v": "to"
      },
      {
        "t": "w",
        "v": "dance"
      },
      {
        "t": "w",
        "v": "wildly"
      },
      {
        "t": "w",
        "v": "in"
      },
      {
        "t": "w",
        "v": "a"
      },
      {
        "t": "w",
        "v": "sexual"
      },
      {
        "t": "w",
        "v": "way"
      },
      {
        "t": "v",
        "n": 8,
        "v": ""
      },
      {
        "t": "w",
        "v": "Twenty"
      },
      {
        "t": "w",
        "v": "three"
      },
      {
        "t": "w",
        "v": "thousand"
      },
      {
        "t": "w",
        "v": "of"
      },
      {
        "t": "w",
        "v": "our"
      },
      {
        "t": "w",
        "v": "Jewish"
      },
      {
        "t": "w",
        "v": "ancestors"
      },
      {
        "t": "w",
        "v": "died"
      },
      {
        "t": "w",
        "v": "in"
      },
      {
        "t": "w",
        "v": "one"
      },
      {
        "t": "w",
        "v": "day"
      },
      {
        "t": "w",
        "v": "because"
      },
      {
        "t": "w",
        "v": "of"
      },
      {
        "t": "w",
        "v": "their"
      },
      {
        "t": "w",
        "v": "sexual"
      },
      {
        "t": "w",
        "v": "immorality"
      },
      {
        "t": "v",
        "n": 9,
        "v": ""
      },
      {
        "t": "w",
        "v": "Let"
      },
      {
        "t": "w",
        "v": "us"
      },
      {
        "t": "w",
        "v": "not"
      },
      {
        "t": "w",
        "v": "test"
      },
      {
        "t": "w",
        "v": "the"
      },
      {
        "t": "w",
        "v": "authority"
      },
      {
        "t": "w",
        "v": "of"
      },
      {
        "t": "w",
        "v": "the"
      },
      {
        "t": "w",
        "v": "Messiah"
      },
      {
        "t": "w",
        "v": "by"
      },
      {
        "t": "w",
        "v": "disobeying"
      },
      {
        "t": "w",
        "v": "him"
      },
      {
        "t": "w",
        "v": "as"
      },
      {
        "t": "w",
        "v": "some"
      },
      {
        "t": "w",
        "v": "of"
      },
      {
        "t": "w",
        "v": "our"
      },
      {
        "t": "w",
        "v": "ancestors"
      },
      {
        "t": "w",
        "v": "did"
      },
      {
        "t": "w",
        "v": "and"
      },
      {
        "t": "w",
        "v": "poisonous"
      },
      {
        "t": "w",
        "v": "snakes"
      },
      {
        "t": "w",
        "v": "killed"
      },
      {
        "t": "w",
        "v": "them"
      },
      {
        "t": "v",
        "n": 10,
        "v": ""
      },
      {
        "t": "w",
        "v": "Do"
      },
      {
        "t": "w",
        "v": "not"
      },
      {
        "t": "w",
        "v": "grumble"
      },
      {
        "t": "w",
        "v": "about"
      },
      {
        "t": "w",
        "v": "what"
      },
      {
        "t": "w",
        "v": "God"
      },
      {
        "t": "w",
        "v": "provides"
      },
      {
        "t": "w",
        "v": "as"
      },
      {
        "t": "w",
        "v": "some"
      },
      {
        "t": "w",
        "v": "of"
      },
      {
        "t": "w",
        "v": "our"
      },
      {
        "t": "w",
        "v": "ancestors"
      },
      {
        "t": "w",
        "v": "did"
      },
      {
        "t": "w",
        "v": "and"
      },
      {
        "t": "w",
        "v": "an"
      },
      {
        "t": "w",
        "v": "angel"
      },
      {
        "t": "w",
        "v": "destroyed"
      },
      {
        "t": "w",
        "v": "them"
      }
    ]
  },
  {
    "t": "p",
    "v": [
      {
        "t": "v",
        "n": 11,
        "v": ""
      },
      {
        "t": "w",
        "v": "Now"
      },
      {
        "t": "w",
        "v": "these"
      },
      {
        "t": "w",
        "v": "things"
      },
      {
        "t": "w",
        "v": "happened"
      },
      {
        "t": "w",
        "v": "to"
      },
      {
        "t": "w",
        "v": "our"
      },
      {
        "t": "w",
        "v": "ancestors"
      },
      {
        "t": "w",
        "v": "they"
      },
      {
        "t": "w",
        "v": "were"
      },
      {
        "t": "w",
        "v": "written"
      },
      {
        "t": "w",
        "v": "so"
      },
      {
        "t": "w",
        "v": "we"
      },
      {
        "t": "w",
        "v": "could"
      },
      {
        "t": "w",
        "v": "learn"
      },
      {
        "t": "w",
        "v": "from"
      },
      {
        "t": "w",
        "v": "them"
      },
      {
        "t": "w",
        "v": "we"
      },
      {
        "t": "w",
        "v": "who"
      },
      {
        "t": "w",
        "v": "are"
      },
      {
        "t": "w",
        "v": "living"
      },
      {
        "t": "w",
        "v": "very"
      },
      {
        "t": "w",
        "v": "close"
      },
      {
        "t": "w",
        "v": "to"
      },
      {
        "t": "w",
        "v": "when"
      },
      {
        "t": "w",
        "v": "the"
      },
      {
        "t": "w",
        "v": "world"
      },
      {
        "t": "w",
        "v": "will"
      },
      {
        "t": "w",
        "v": "end"
      },
      {
        "t": "v",
        "n": 12,
        "v": ""
      },
      {
        "t": "w",
        "v": "And"
      },
      {
        "t": "w",
        "v": "so"
      },
      {
        "t": "w",
        "v": "the"
      },
      {
        "t": "w",
        "v": "lesson"
      },
      {
        "t": "w",
        "v": "is"
      },
      {
        "t": "w",
        "v": "this"
      },
      {
        "t": "w",
        "v": "If"
      },
      {
        "t": "w",
        "v": "you"
      },
      {
        "t": "w",
        "v": "think"
      },
      {
        "t": "w",
        "v": "you"
      },
      {
        "t": "w",
        "v": "are"
      },
      {
        "t": "w",
        "v": "strong"
      },
      {
        "t": "w",
        "v": "and"
      },
      {
        "t": "w",
        "v": "are"
      },
      {
        "t": "w",
        "v": "standing"
      },
      {
        "t": "w",
        "v": "strong"
      },
      {
        "t": "w",
        "v": "be"
      },
      {
        "t": "w",
        "v": "very"
      },
      {
        "t": "w",
        "v": "careful"
      },
      {
        "t": "w",
        "v": "because"
      },
      {
        "t": "w",
        "v": "this"
      },
      {
        "t": "w",
        "v": "is"
      },
      {
        "t": "w",
        "v": "just"
      },
      {
        "t": "w",
        "v": "when"
      },
      {
        "t": "w",
        "v": "you"
      },
      {
        "t": "w",
        "v": "may"
      },
      {
        "t": "w",
        "v": "fall"
      },
      {
        "t": "v",
        "n": 13,
        "v": ""
      },
      {
        "t": "w",
        "v": "Every"
      },
      {
        "t": "w",
        "v": "temptation"
      },
      {
        "t": "w",
        "v": "you"
      },
      {
        "t": "w",
        "v": "have"
      },
      {
        "t": "w",
        "v": "fought"
      },
      {
        "t": "w",
        "v": "against"
      },
      {
        "t": "w",
        "v": "is"
      },
      {
        "t": "w",
        "v": "shared"
      },
      {
        "t": "w",
        "v": "by"
      },
      {
        "t": "w",
        "v": "us"
      },
      {
        "t": "w",
        "v": "all"
      },
      {
        "t": "w",
        "v": "but"
      },
      {
        "t": "w",
        "v": "God"
      },
      {
        "t": "w",
        "v": "has"
      },
      {
        "t": "w",
        "v": "given"
      },
      {
        "t": "w",
        "v": "us"
      },
      {
        "t": "w",
        "v": "his"
      },
      {
        "t": "w",
        "v": "promise"
      },
      {
        "t": "w",
        "v": "and"
      },
      {
        "t": "w",
        "v": "he"
      },
      {
        "t": "w",
        "v": "will"
      },
      {
        "t": "w",
        "v": "not"
      },
      {
        "t": "w",
        "v": "permit"
      },
      {
        "t": "w",
        "v": "the"
      },
      {
        "t": "w",
        "v": "temptation"
      },
      {
        "t": "w",
        "v": "to"
      },
      {
        "t": "w",
        "v": "be"
      },
      {
        "t": "w",
        "v": "greater"
      },
      {
        "t": "w",
        "v": "than"
      },
      {
        "t": "w",
        "v": "your"
      },
      {
        "t": "w",
        "v": "ability"
      },
      {
        "t": "w",
        "v": "to"
      },
      {
        "t": "w",
        "v": "fight"
      },
      {
        "t": "w",
        "v": "against"
      },
      {
        "t": "w",
        "v": "the"
      },
      {
        "t": "w",
        "v": "sin"
      },
      {
        "t": "w",
        "v": "When"
      },
      {
        "t": "w",
        "v": "the"
      },
      {
        "t": "w",
        "v": "temptation"
      },
      {
        "t": "w",
        "v": "comes"
      },
      {
        "t": "w",
        "v": "God"
      },
      {
        "t": "w",
        "v": "will"
      },
      {
        "t": "w",
        "v": "provide"
      },
      {
        "t": "w",
        "v": "a"
      },
      {
        "t": "w",
        "v": "way"
      },
      {
        "t": "w",
        "v": "for"
      },
      {
        "t": "w",
        "v": "you"
      },
      {
        "t": "w",
        "v": "to"
      },
      {
        "t": "w",
        "v": "get"
      },
      {
        "t": "w",
        "v": "free"
      },
      {
        "t": "w",
        "v": "of"
      },
      {
        "t": "w",
        "v": "it"
      },
      {
        "t": "w",
        "v": "so"
      },
      {
        "t": "w",
        "v": "you"
      },
      {
        "t": "w",
        "v": "may"
      },
      {
        "t": "w",
        "v": "endure"
      },
      {
        "t": "w",
        "v": "the"
      },
      {
        "t": "w",
        "v": "temptation"
      },
      {
        "t": "w",
        "v": "to"
      },
      {
        "t": "w",
        "v": "sin"
      }
    ]
  },
  {
    "t": "p",
    "v": [
      {
        "t": "v",
        "n": 14,
        "v": ""
      },
      {
        "t": "w",
        "v": "Therefore"
      },
      {
        "t": "w",
        "v": "my"
      },
      {
        "t": "w",
        "v": "loved"
      },
      {
        "t": "w",
        "v": "ones"
      },
      {
        "t": "w",
        "v": "run"
      },
      {
        "t": "w",
        "v": "away"
      },
      {
        "t": "w",
        "v": "as"
      },
      {
        "t": "w",
        "v": "fast"
      },
      {
        "t": "w",
        "v": "as"
      },
      {
        "t": "w",
        "v": "you"
      },
      {
        "t": "w",
        "v": "can"
      },
      {
        "t": "w",
        "v": "from"
      },
      {
        "t": "w",
        "v": "idol"
      },
      {
        "t": "w",
        "v": "worship"
      },
      {
        "t": "v",
        "n": 15,
        "v": ""
      },
      {
        "t": "w",
        "v": "I"
      },
      {
        "t": "w",
        "v": "speak"
      },
      {
        "t": "w",
        "v": "to"
      },
      {
        "t": "w",
        "v": "you"
      },
      {
        "t": "w",
        "v": "as"
      },
      {
        "t": "w",
        "v": "people"
      },
      {
        "t": "w",
        "v": "who"
      },
      {
        "t": "w",
        "v": "consider"
      },
      {
        "t": "w",
        "v": "carefully"
      },
      {
        "t": "w",
        "v": "how"
      },
      {
        "t": "w",
        "v": "you"
      },
      {
        "t": "w",
        "v": "live"
      },
      {
        "t": "w",
        "v": "think"
      },
      {
        "t": "w",
        "v": "about"
      },
      {
        "t": "w",
        "v": "what"
      },
      {
        "t": "w",
        "v": "I"
      },
      {
        "t": "w",
        "v": "am"
      },
      {
        "t": "w",
        "v": "saying"
      },
      {
        "t": "w",
        "v": "here"
      },
      {
        "t": "v",
        "n": 16,
        "v": ""
      },
      {
        "t": "w",
        "v": "When"
      },
      {
        "t": "w",
        "v": "we"
      },
      {
        "t": "w",
        "v": "drink"
      },
      {
        "t": "w",
        "v": "the"
      },
      {
        "t": "w",
        "v": "cup"
      },
      {
        "t": "w",
        "v": "of"
      },
      {
        "t": "w",
        "v": "wine"
      },
      {
        "t": "w",
        "v": "that"
      },
      {
        "t": "w",
        "v": "we"
      },
      {
        "t": "w",
        "v": "bless"
      },
      {
        "t": "w",
        "v": "we"
      },
      {
        "t": "w",
        "v": "share"
      },
      {
        "t": "w",
        "v": "in"
      },
      {
        "t": "w",
        "v": "the"
      },
      {
        "t": "w",
        "v": "blood"
      },
      {
        "t": "w",
        "v": "of"
      },
      {
        "t": "w",
        "v": "the"
      },
      {
        "t": "w",
        "v": "Messiah"
      },
      {
        "t": "w",
        "v": "When"
      },
      {
        "t": "w",
        "v": "we"
      },
      {
        "t": "w",
        "v": "break"
      },
      {
        "t": "w",
        "v": "the"
      },
      {
        "t": "w",
        "v": "bread"
      },
      {
        "t": "w",
        "v": "we"
      },
      {
        "t": "w",
        "v": "share"
      },
      {
        "t": "w",
        "v": "in"
      },
      {
        "t": "w",
        "v": "the"
      },
      {
        "t": "w",
        "v": "body"
      },
      {
        "t": "w",
        "v": "of"
      },
      {
        "t": "w",
        "v": "the"
      },
      {
        "t": "w",
        "v": "Messiah"
      },
      {
        "t": "v",
        "n": 17,
        "v": ""
      },
      {
        "t": "w",
        "v": "There"
      },
      {
        "t": "w",
        "v": "is"
      },
      {
        "t": "w",
        "v": "only"
      },
      {
        "t": "w",
        "v": "one"
      },
      {
        "t": "w",
        "v": "loaf"
      },
      {
        "t": "w",
        "v": "of"
      },
      {
        "t": "w",
        "v": "bread"
      },
      {
        "t": "w",
        "v": "and"
      },
      {
        "t": "w",
        "v": "we"
      },
      {
        "t": "w",
        "v": "although"
      },
      {
        "t": "w",
        "v": "we"
      },
      {
        "t": "w",
        "v": "are"
      },
      {
        "t": "w",
        "v": "many"
      },
      {
        "t": "w",
        "v": "all"
      },
      {
        "t": "w",
        "v": "make"
      },
      {
        "t": "w",
        "v": "up"
      },
      {
        "t": "w",
        "v": "just"
      },
      {
        "t": "w",
        "v": "one"
      },
      {
        "t": "w",
        "v": "body"
      },
      {
        "t": "w",
        "v": "together"
      },
      {
        "t": "w",
        "v": "and"
      },
      {
        "t": "w",
        "v": "we"
      },
      {
        "t": "w",
        "v": "all"
      },
      {
        "t": "w",
        "v": "take"
      },
      {
        "t": "w",
        "v": "and"
      },
      {
        "t": "w",
        "v": "eat"
      },
      {
        "t": "w",
        "v": "from"
      },
      {
        "t": "w",
        "v": "the"
      },
      {
        "t": "w",
        "v": "one"
      },
      {
        "t": "w",
        "v": "loaf"
      },
      {
        "t": "w",
        "v": "of"
      },
      {
        "t": "w",
        "v": "bread"
      },
      {
        "t": "w",
        "v": "together"
      }
    ]
  },
  {
    "t": "p",
    "v": [
      {
        "t": "v",
        "n": 18,
        "v": ""
      },
      {
        "t": "w",
        "v": "Think"
      },
      {
        "t": "w",
        "v": "about"
      },
      {
        "t": "w",
        "v": "the"
      },
      {
        "t": "w",
        "v": "people"
      },
      {
        "t": "w",
        "v": "of"
      },
      {
        "t": "w",
        "v": "Israel"
      },
      {
        "t": "w",
        "v": "Those"
      },
      {
        "t": "w",
        "v": "who"
      },
      {
        "t": "w",
        "v": "eat"
      },
      {
        "t": "w",
        "v": "the"
      },
      {
        "t": "w",
        "v": "sacrifices"
      },
      {
        "t": "w",
        "v": "at"
      },
      {
        "t": "w",
        "v": "the"
      },
      {
        "t": "w",
        "v": "altar"
      },
      {
        "t": "w",
        "v": "share"
      },
      {
        "t": "w",
        "v": "in"
      },
      {
        "t": "w",
        "v": "the"
      },
      {
        "t": "w",
        "v": "altar"
      },
      {
        "t": "v",
        "n": 19,
        "v": ""
      },
      {
        "t": "w",
        "v": "So"
      },
      {
        "t": "w",
        "v": "I"
      },
      {
        "t": "w",
        "v": "am"
      },
      {
        "t": "w",
        "v": "saying"
      },
      {
        "t": "w",
        "v": "that"
      },
      {
        "t": "w",
        "v": "an"
      },
      {
        "t": "w",
        "v": "idol"
      },
      {
        "t": "w",
        "v": "is"
      },
      {
        "t": "w",
        "v": "not"
      },
      {
        "t": "w",
        "v": "something"
      },
      {
        "t": "w",
        "v": "real"
      },
      {
        "t": "w",
        "v": "and"
      },
      {
        "t": "w",
        "v": "to"
      },
      {
        "t": "w",
        "v": "eat"
      },
      {
        "t": "w",
        "v": "food"
      },
      {
        "t": "w",
        "v": "sacrificed"
      },
      {
        "t": "w",
        "v": "to"
      },
      {
        "t": "w",
        "v": "an"
      },
      {
        "t": "w",
        "v": "idol"
      },
      {
        "t": "w",
        "v": "is"
      },
      {
        "t": "w",
        "v": "not"
      },
      {
        "t": "w",
        "v": "significant"
      },
      {
        "t": "w",
        "v": "But"
      },
      {
        "t": "w",
        "v": "even"
      },
      {
        "t": "w",
        "v": "so"
      },
      {
        "t": "w",
        "v": "there"
      },
      {
        "t": "w",
        "v": "are"
      },
      {
        "t": "w",
        "v": "important"
      },
      {
        "t": "w",
        "v": "issues"
      },
      {
        "t": "w",
        "v": "here"
      },
      {
        "t": "v",
        "n": 20,
        "v": ""
      },
      {
        "t": "w",
        "v": "What"
      },
      {
        "t": "w",
        "v": "I"
      },
      {
        "t": "w",
        "v": "mean"
      },
      {
        "t": "w",
        "v": "is"
      },
      {
        "t": "w",
        "v": "this"
      },
      {
        "t": "w",
        "v": "When"
      },
      {
        "t": "w",
        "v": "non"
      },
      {
        "t": "w",
        "v": "Jews"
      },
      {
        "t": "w",
        "v": "make"
      },
      {
        "t": "w",
        "v": "their"
      },
      {
        "t": "w",
        "v": "sacrifices"
      },
      {
        "t": "w",
        "v": "they"
      },
      {
        "t": "w",
        "v": "are"
      },
      {
        "t": "w",
        "v": "really"
      },
      {
        "t": "w",
        "v": "making"
      },
      {
        "t": "w",
        "v": "them"
      },
      {
        "t": "w",
        "v": "to"
      },
      {
        "t": "w",
        "v": "demons"
      },
      {
        "t": "w",
        "v": "and"
      },
      {
        "t": "w",
        "v": "not"
      },
      {
        "t": "w",
        "v": "to"
      },
      {
        "t": "w",
        "v": "God"
      },
      {
        "t": "w",
        "v": "at"
      },
      {
        "t": "w",
        "v": "all"
      },
      {
        "t": "w",
        "v": "And"
      },
      {
        "t": "w",
        "v": "I"
      },
      {
        "t": "w",
        "v": "do"
      },
      {
        "t": "w",
        "v": "not"
      },
      {
        "t": "w",
        "v": "wish"
      },
      {
        "t": "w",
        "v": "that"
      },
      {
        "t": "w",
        "v": "you"
      },
      {
        "t": "w",
        "v": "share"
      },
      {
        "t": "w",
        "v": "anything"
      },
      {
        "t": "w",
        "v": "with"
      },
      {
        "t": "w",
        "v": "demons"
      },
      {
        "t": "v",
        "n": 21,
        "v": ""
      },
      {
        "t": "w",
        "v": "You"
      },
      {
        "t": "w",
        "v": "must"
      },
      {
        "t": "w",
        "v": "not"
      },
      {
        "t": "w",
        "v": "drink"
      },
      {
        "t": "w",
        "v": "from"
      },
      {
        "t": "w",
        "v": "the"
      },
      {
        "t": "w",
        "v": "Lord"
      },
      {
        "t": "w",
        "v": "s"
      },
      {
        "t": "w",
        "v": "cup"
      },
      {
        "t": "w",
        "v": "and"
      },
      {
        "t": "w",
        "v": "then"
      },
      {
        "t": "w",
        "v": "later"
      },
      {
        "t": "w",
        "v": "drink"
      },
      {
        "t": "w",
        "v": "the"
      },
      {
        "t": "w",
        "v": "cup"
      },
      {
        "t": "w",
        "v": "of"
      },
      {
        "t": "w",
        "v": "demons"
      },
      {
        "t": "w",
        "v": "You"
      },
      {
        "t": "w",
        "v": "must"
      },
      {
        "t": "w",
        "v": "not"
      },
      {
        "t": "w",
        "v": "share"
      },
      {
        "t": "w",
        "v": "in"
      },
      {
        "t": "w",
        "v": "the"
      },
      {
        "t": "w",
        "v": "Lord"
      },
      {
        "t": "w",
        "v": "s"
      },
      {
        "t": "w",
        "v": "supper"
      },
      {
        "t": "w",
        "v": "and"
      },
      {
        "t": "w",
        "v": "then"
      },
      {
        "t": "w",
        "v": "later"
      },
      {
        "t": "w",
        "v": "eat"
      },
      {
        "t": "w",
        "v": "a"
      },
      {
        "t": "w",
        "v": "meal"
      },
      {
        "t": "w",
        "v": "with"
      },
      {
        "t": "w",
        "v": "demons"
      },
      {
        "t": "v",
        "n": 22,
        "v": ""
      },
      {
        "t": "w",
        "v": "To"
      },
      {
        "t": "w",
        "v": "do"
      },
      {
        "t": "w",
        "v": "so"
      },
      {
        "t": "w",
        "v": "would"
      },
      {
        "t": "w",
        "v": "provoke"
      },
      {
        "t": "w",
        "v": "the"
      },
      {
        "t": "w",
        "v": "Lord"
      },
      {
        "t": "w",
        "v": "to"
      },
      {
        "t": "w",
        "v": "become"
      },
      {
        "t": "w",
        "v": "jealous"
      },
      {
        "t": "w",
        "v": "about"
      },
      {
        "t": "w",
        "v": "split"
      },
      {
        "t": "w",
        "v": "loyalty"
      },
      {
        "t": "w",
        "v": "You"
      },
      {
        "t": "w",
        "v": "are"
      },
      {
        "t": "w",
        "v": "not"
      },
      {
        "t": "w",
        "v": "stronger"
      },
      {
        "t": "w",
        "v": "than"
      },
      {
        "t": "w",
        "v": "he"
      },
      {
        "t": "w",
        "v": "is"
      }
    ]
  },
  {
    "t": "p",
    "v": [
      {
        "t": "v",
        "n": 23,
        "v": ""
      },
      {
        "t": "w",
        "v": "Some"
      },
      {
        "t": "w",
        "v": "say"
      },
      {
        "t": "w",
        "v": "Everything"
      },
      {
        "t": "w",
        "v": "is"
      },
      {
        "t": "w",
        "v": "lawful"
      },
      {
        "t": "w",
        "v": "but"
      },
      {
        "t": "w",
        "v": "not"
      },
      {
        "t": "w",
        "v": "everything"
      },
      {
        "t": "w",
        "v": "is"
      },
      {
        "t": "w",
        "v": "for"
      },
      {
        "t": "w",
        "v": "our"
      },
      {
        "t": "w",
        "v": "good"
      },
      {
        "t": "w",
        "v": "or"
      },
      {
        "t": "w",
        "v": "for"
      },
      {
        "t": "w",
        "v": "the"
      },
      {
        "t": "w",
        "v": "good"
      },
      {
        "t": "w",
        "v": "of"
      },
      {
        "t": "w",
        "v": "other"
      },
      {
        "t": "w",
        "v": "people"
      },
      {
        "t": "w",
        "v": "Yes"
      },
      {
        "t": "w",
        "v": "everything"
      },
      {
        "t": "w",
        "v": "is"
      },
      {
        "t": "w",
        "v": "lawful"
      },
      {
        "t": "w",
        "v": "but"
      },
      {
        "t": "w",
        "v": "not"
      },
      {
        "t": "w",
        "v": "everything"
      },
      {
        "t": "w",
        "v": "helps"
      },
      {
        "t": "w",
        "v": "people"
      },
      {
        "t": "w",
        "v": "to"
      },
      {
        "t": "w",
        "v": "grow"
      },
      {
        "t": "w",
        "v": "strong"
      },
      {
        "t": "w",
        "v": "in"
      },
      {
        "t": "w",
        "v": "their"
      },
      {
        "t": "w",
        "v": "life"
      },
      {
        "t": "w",
        "v": "with"
      },
      {
        "t": "w",
        "v": "God"
      },
      {
        "t": "v",
        "n": 24,
        "v": ""
      },
      {
        "t": "w",
        "v": "Do"
      },
      {
        "t": "w",
        "v": "not"
      },
      {
        "t": "w",
        "v": "work"
      },
      {
        "t": "w",
        "v": "for"
      },
      {
        "t": "w",
        "v": "your"
      },
      {
        "t": "w",
        "v": "good"
      },
      {
        "t": "w",
        "v": "only"
      },
      {
        "t": "w",
        "v": "but"
      },
      {
        "t": "w",
        "v": "also"
      },
      {
        "t": "w",
        "v": "for"
      },
      {
        "t": "w",
        "v": "the"
      },
      {
        "t": "w",
        "v": "good"
      },
      {
        "t": "w",
        "v": "of"
      },
      {
        "t": "w",
        "v": "other"
      },
      {
        "t": "w",
        "v": "people"
      },
      {
        "t": "w",
        "v": "All"
      },
      {
        "t": "w",
        "v": "of"
      },
      {
        "t": "w",
        "v": "us"
      },
      {
        "t": "w",
        "v": "must"
      },
      {
        "t": "w",
        "v": "act"
      },
      {
        "t": "w",
        "v": "toward"
      },
      {
        "t": "w",
        "v": "everyone"
      },
      {
        "t": "w",
        "v": "in"
      },
      {
        "t": "w",
        "v": "such"
      },
      {
        "t": "w",
        "v": "a"
      },
      {
        "t": "w",
        "v": "way"
      },
      {
        "t": "w",
        "v": "as"
      },
      {
        "t": "w",
        "v": "to"
      },
      {
        "t": "w",
        "v": "help"
      },
      {
        "t": "w",
        "v": "them"
      },
      {
        "t": "w",
        "v": "all"
      },
      {
        "t": "v",
        "n": 25,
        "v": ""
      },
      {
        "t": "w",
        "v": "Here"
      },
      {
        "t": "w",
        "v": "is"
      },
      {
        "t": "w",
        "v": "our"
      },
      {
        "t": "w",
        "v": "rule"
      },
      {
        "t": "w",
        "v": "You"
      },
      {
        "t": "w",
        "v": "may"
      },
      {
        "t": "w",
        "v": "buy"
      },
      {
        "t": "w",
        "v": "and"
      },
      {
        "t": "w",
        "v": "eat"
      },
      {
        "t": "w",
        "v": "whatever"
      },
      {
        "t": "w",
        "v": "meat"
      },
      {
        "t": "w",
        "v": "you"
      },
      {
        "t": "w",
        "v": "want"
      },
      {
        "t": "w",
        "v": "in"
      },
      {
        "t": "w",
        "v": "the"
      },
      {
        "t": "w",
        "v": "market"
      },
      {
        "t": "w",
        "v": "without"
      },
      {
        "t": "w",
        "v": "having"
      },
      {
        "t": "w",
        "v": "to"
      },
      {
        "t": "w",
        "v": "ask"
      },
      {
        "t": "w",
        "v": "whether"
      },
      {
        "t": "w",
        "v": "it"
      },
      {
        "t": "w",
        "v": "was"
      },
      {
        "t": "w",
        "v": "sacrificed"
      },
      {
        "t": "w",
        "v": "to"
      },
      {
        "t": "w",
        "v": "idols"
      },
      {
        "t": "w",
        "v": "or"
      },
      {
        "t": "w",
        "v": "not"
      },
      {
        "t": "v",
        "n": 26,
        "v": ""
      },
      {
        "t": "w",
        "v": "As"
      },
      {
        "t": "w",
        "v": "the"
      },
      {
        "t": "w",
        "v": "psalmist"
      },
      {
        "t": "w",
        "v": "says"
      },
      {
        "t": "w",
        "v": "The"
      },
      {
        "t": "w",
        "v": "earth"
      },
      {
        "t": "w",
        "v": "is"
      },
      {
        "t": "w",
        "v": "the"
      },
      {
        "t": "w",
        "v": "Lord"
      },
      {
        "t": "w",
        "v": "s"
      },
      {
        "t": "w",
        "v": "and"
      },
      {
        "t": "w",
        "v": "everything"
      },
      {
        "t": "w",
        "v": "in"
      },
      {
        "t": "w",
        "v": "it"
      },
      {
        "t": "v",
        "n": 27,
        "v": ""
      },
      {
        "t": "w",
        "v": "If"
      },
      {
        "t": "w",
        "v": "a"
      },
      {
        "t": "w",
        "v": "non"
      },
      {
        "t": "w",
        "v": "Jewish"
      },
      {
        "t": "w",
        "v": "unbeliever"
      },
      {
        "t": "w",
        "v": "invites"
      },
      {
        "t": "w",
        "v": "you"
      },
      {
        "t": "w",
        "v": "to"
      },
      {
        "t": "w",
        "v": "a"
      },
      {
        "t": "w",
        "v": "meal"
      },
      {
        "t": "w",
        "v": "and"
      },
      {
        "t": "w",
        "v": "you"
      },
      {
        "t": "w",
        "v": "desire"
      },
      {
        "t": "w",
        "v": "to"
      },
      {
        "t": "w",
        "v": "go"
      },
      {
        "t": "w",
        "v": "eat"
      },
      {
        "t": "w",
        "v": "whatever"
      },
      {
        "t": "w",
        "v": "he"
      },
      {
        "t": "w",
        "v": "serves"
      },
      {
        "t": "w",
        "v": "you"
      },
      {
        "t": "w",
        "v": "God"
      },
      {
        "t": "w",
        "v": "does"
      },
      {
        "t": "w",
        "v": "not"
      },
      {
        "t": "w",
        "v": "require"
      },
      {
        "t": "w",
        "v": "you"
      },
      {
        "t": "w",
        "v": "to"
      },
      {
        "t": "w",
        "v": "ask"
      },
      {
        "t": "w",
        "v": "him"
      },
      {
        "t": "w",
        "v": "about"
      },
      {
        "t": "w",
        "v": "where"
      },
      {
        "t": "w",
        "v": "he"
      },
      {
        "t": "w",
        "v": "purchased"
      },
      {
        "t": "w",
        "v": "the"
      },
      {
        "t": "w",
        "v": "food"
      },
      {
        "t": "v",
        "n": 28,
        "v": ""
      },
      {
        "t": "w",
        "v": "But"
      },
      {
        "t": "w",
        "v": "if"
      },
      {
        "t": "w",
        "v": "someone"
      },
      {
        "t": "w",
        "v": "says"
      },
      {
        "t": "w",
        "v": "to"
      },
      {
        "t": "w",
        "v": "you"
      },
      {
        "t": "w",
        "v": "We"
      },
      {
        "t": "w",
        "v": "bought"
      },
      {
        "t": "w",
        "v": "this"
      },
      {
        "t": "w",
        "v": "food"
      },
      {
        "t": "w",
        "v": "at"
      },
      {
        "t": "w",
        "v": "the"
      },
      {
        "t": "w",
        "v": "idol"
      },
      {
        "t": "w",
        "v": "temple"
      },
      {
        "t": "w",
        "v": "and"
      },
      {
        "t": "w",
        "v": "it"
      },
      {
        "t": "w",
        "v": "was"
      },
      {
        "t": "w",
        "v": "sacrificed"
      },
      {
        "t": "w",
        "v": "to"
      },
      {
        "t": "w",
        "v": "the"
      },
      {
        "t": "w",
        "v": "gods"
      },
      {
        "t": "w",
        "v": "then"
      },
      {
        "t": "w",
        "v": "do"
      },
      {
        "t": "w",
        "v": "not"
      },
      {
        "t": "w",
        "v": "eat"
      },
      {
        "t": "w",
        "v": "the"
      },
      {
        "t": "w",
        "v": "food"
      },
      {
        "t": "w",
        "v": "for"
      },
      {
        "t": "w",
        "v": "the"
      },
      {
        "t": "w",
        "v": "good"
      },
      {
        "t": "w",
        "v": "of"
      },
      {
        "t": "w",
        "v": "the"
      },
      {
        "t": "w",
        "v": "person"
      },
      {
        "t": "w",
        "v": "who"
      },
      {
        "t": "w",
        "v": "served"
      },
      {
        "t": "w",
        "v": "it"
      },
      {
        "t": "w",
        "v": "and"
      },
      {
        "t": "w",
        "v": "so"
      },
      {
        "t": "w",
        "v": "as"
      },
      {
        "t": "w",
        "v": "not"
      },
      {
        "t": "w",
        "v": "to"
      },
      {
        "t": "w",
        "v": "cause"
      },
      {
        "t": "w",
        "v": "conflict"
      },
      {
        "t": "w",
        "v": "in"
      },
      {
        "t": "w",
        "v": "the"
      },
      {
        "t": "w",
        "v": "sense"
      },
      {
        "t": "w",
        "v": "of"
      },
      {
        "t": "w",
        "v": "right"
      },
      {
        "t": "w",
        "v": "and"
      },
      {
        "t": "w",
        "v": "wrong"
      },
      {
        "t": "v",
        "n": 29,
        "v": ""
      },
      {
        "t": "w",
        "v": "This"
      },
      {
        "t": "w",
        "v": "is"
      },
      {
        "t": "w",
        "v": "being"
      },
      {
        "t": "w",
        "v": "careful"
      },
      {
        "t": "w",
        "v": "about"
      },
      {
        "t": "w",
        "v": "how"
      },
      {
        "t": "w",
        "v": "that"
      },
      {
        "t": "w",
        "v": "other"
      },
      {
        "t": "w",
        "v": "person"
      },
      {
        "t": "w",
        "v": "thinks"
      },
      {
        "t": "w",
        "v": "about"
      },
      {
        "t": "w",
        "v": "right"
      },
      {
        "t": "w",
        "v": "and"
      },
      {
        "t": "w",
        "v": "wrong"
      },
      {
        "t": "w",
        "v": "not"
      },
      {
        "t": "w",
        "v": "how"
      },
      {
        "t": "w",
        "v": "you"
      },
      {
        "t": "w",
        "v": "think"
      },
      {
        "t": "w",
        "v": "about"
      },
      {
        "t": "w",
        "v": "it"
      },
      {
        "t": "w",
        "v": "My"
      },
      {
        "t": "w",
        "v": "personal"
      },
      {
        "t": "w",
        "v": "choices"
      },
      {
        "t": "w",
        "v": "are"
      },
      {
        "t": "w",
        "v": "not"
      },
      {
        "t": "w",
        "v": "to"
      },
      {
        "t": "w",
        "v": "be"
      },
      {
        "t": "w",
        "v": "changed"
      },
      {
        "t": "w",
        "v": "by"
      },
      {
        "t": "w",
        "v": "what"
      },
      {
        "t": "w",
        "v": "another"
      },
      {
        "t": "w",
        "v": "person"
      },
      {
        "t": "w",
        "v": "believes"
      },
      {
        "t": "w",
        "v": "is"
      },
      {
        "t": "w",
        "v": "right"
      },
      {
        "t": "w",
        "v": "or"
      },
      {
        "t": "w",
        "v": "wrong"
      },
      {
        "t": "v",
        "n": 30,
        "v": ""
      },
      {
        "t": "w",
        "v": "If"
      },
      {
        "t": "w",
        "v": "I"
      },
      {
        "t": "w",
        "v": "enjoy"
      },
      {
        "t": "w",
        "v": "the"
      },
      {
        "t": "w",
        "v": "meal"
      },
      {
        "t": "w",
        "v": "with"
      },
      {
        "t": "w",
        "v": "thanksgiving"
      },
      {
        "t": "w",
        "v": "I"
      },
      {
        "t": "w",
        "v": "should"
      },
      {
        "t": "w",
        "v": "not"
      },
      {
        "t": "w",
        "v": "permit"
      },
      {
        "t": "w",
        "v": "someone"
      },
      {
        "t": "w",
        "v": "else"
      },
      {
        "t": "w",
        "v": "to"
      },
      {
        "t": "w",
        "v": "condemn"
      },
      {
        "t": "w",
        "v": "me"
      }
    ]
  },
  {
    "t": "p",
    "v": [
      {
        "t": "v",
        "n": 31,
        "v": ""
      },
      {
        "t": "w",
        "v": "The"
      },
      {
        "t": "w",
        "v": "rule"
      },
      {
        "t": "w",
        "v": "here"
      },
      {
        "t": "w",
        "v": "is"
      },
      {
        "t": "w",
        "v": "that"
      },
      {
        "t": "w",
        "v": "whether"
      },
      {
        "t": "w",
        "v": "you"
      },
      {
        "t": "w",
        "v": "eat"
      },
      {
        "t": "w",
        "v": "a"
      },
      {
        "t": "w",
        "v": "meal"
      },
      {
        "t": "w",
        "v": "or"
      },
      {
        "t": "w",
        "v": "drink"
      },
      {
        "t": "w",
        "v": "something"
      },
      {
        "t": "w",
        "v": "offered"
      },
      {
        "t": "w",
        "v": "to"
      },
      {
        "t": "w",
        "v": "you"
      },
      {
        "t": "w",
        "v": "or"
      },
      {
        "t": "w",
        "v": "whatever"
      },
      {
        "t": "w",
        "v": "you"
      },
      {
        "t": "w",
        "v": "do"
      },
      {
        "t": "w",
        "v": "do"
      },
      {
        "t": "w",
        "v": "everything"
      },
      {
        "t": "w",
        "v": "in"
      },
      {
        "t": "w",
        "v": "a"
      },
      {
        "t": "w",
        "v": "way"
      },
      {
        "t": "w",
        "v": "so"
      },
      {
        "t": "w",
        "v": "that"
      },
      {
        "t": "w",
        "v": "you"
      },
      {
        "t": "w",
        "v": "give"
      },
      {
        "t": "w",
        "v": "praise"
      },
      {
        "t": "w",
        "v": "to"
      },
      {
        "t": "w",
        "v": "God"
      },
      {
        "t": "v",
        "n": 32,
        "v": ""
      },
      {
        "t": "w",
        "v": "Do"
      },
      {
        "t": "w",
        "v": "not"
      },
      {
        "t": "w",
        "v": "be"
      },
      {
        "t": "w",
        "v": "offensive"
      },
      {
        "t": "w",
        "v": "to"
      },
      {
        "t": "w",
        "v": "Jews"
      },
      {
        "t": "w",
        "v": "or"
      },
      {
        "t": "w",
        "v": "to"
      },
      {
        "t": "w",
        "v": "Greeks"
      },
      {
        "t": "w",
        "v": "nor"
      },
      {
        "t": "w",
        "v": "even"
      },
      {
        "t": "w",
        "v": "to"
      },
      {
        "t": "w",
        "v": "those"
      },
      {
        "t": "w",
        "v": "in"
      },
      {
        "t": "w",
        "v": "the"
      },
      {
        "t": "w",
        "v": "church"
      },
      {
        "t": "w",
        "v": "of"
      },
      {
        "t": "w",
        "v": "God"
      },
      {
        "t": "w",
        "v": "about"
      },
      {
        "t": "w",
        "v": "matters"
      },
      {
        "t": "w",
        "v": "such"
      },
      {
        "t": "w",
        "v": "as"
      },
      {
        "t": "w",
        "v": "these"
      },
      {
        "t": "v",
        "n": 33,
        "v": ""
      },
      {
        "t": "w",
        "v": "I"
      },
      {
        "t": "w",
        "v": "make"
      },
      {
        "t": "w",
        "v": "it"
      },
      {
        "t": "w",
        "v": "my"
      },
      {
        "t": "w",
        "v": "duty"
      },
      {
        "t": "w",
        "v": "to"
      },
      {
        "t": "w",
        "v": "please"
      },
      {
        "t": "w",
        "v": "everyone"
      },
      {
        "t": "w",
        "v": "I"
      },
      {
        "t": "w",
        "v": "can"
      },
      {
        "t": "w",
        "v": "in"
      },
      {
        "t": "w",
        "v": "every"
      },
      {
        "t": "w",
        "v": "way"
      },
      {
        "t": "w",
        "v": "that"
      },
      {
        "t": "w",
        "v": "is"
      },
      {
        "t": "w",
        "v": "possible"
      },
      {
        "t": "w",
        "v": "I"
      },
      {
        "t": "w",
        "v": "do"
      },
      {
        "t": "w",
        "v": "this"
      },
      {
        "t": "w",
        "v": "by"
      },
      {
        "t": "w",
        "v": "not"
      },
      {
        "t": "w",
        "v": "seeking"
      },
      {
        "t": "w",
        "v": "my"
      },
      {
        "t": "w",
        "v": "own"
      },
      {
        "t": "w",
        "v": "good"
      },
      {
        "t": "w",
        "v": "Instead"
      },
      {
        "t": "w",
        "v": "I"
      },
      {
        "t": "w",
        "v": "try"
      },
      {
        "t": "w",
        "v": "to"
      },
      {
        "t": "w",
        "v": "build"
      },
      {
        "t": "w",
        "v": "up"
      },
      {
        "t": "w",
        "v": "other"
      },
      {
        "t": "w",
        "v": "people"
      },
      {
        "t": "w",
        "v": "by"
      },
      {
        "t": "w",
        "v": "helping"
      },
      {
        "t": "w",
        "v": "them"
      },
      {
        "t": "w",
        "v": "so"
      },
      {
        "t": "w",
        "v": "that"
      },
      {
        "t": "w",
        "v": "God"
      },
      {
        "t": "w",
        "v": "might"
      },
      {
        "t": "w",
        "v": "save"
      },
      {
        "t": "w",
        "v": "them"
      }
    ]
  }
]