[
  {
    "t": "q",
    "v": [
      {
        "t": "v",
        "n": 1,
        "v": "Call your male fellow Israelites, ‘You are Yahweh’s people,’ and call your female fellow Israelites, ‘Yahweh has been kind to you.’”",
        "id": 1
      }
    ],
    "id": 0
  },
  {
    "t": "q",
    "v": [
      {
        "t": "v",
        "n": 2,
        "v": "Yahweh said to me, “I want you to accuse Israel, who is like a mother to you, of being like an unfaithful wife to me.",
        "id": 3
      }
    ],
    "id": 2
  },
  {
    "t": "q",
    "v": [
      {
        "t": "t",
        "v": "This nation is no longer like a wife to me,",
        "id": 5
      }
    ],
    "id": 4
  },
  {
    "t": "q",
    "v": [
      {
        "t": "t",
        "v": "and I am no longer like a husband to her.",
        "id": 7
      }
    ],
    "id": 6
  },
  {
    "t": "q",
    "v": [
      {
        "t": "t",
        "v": "Tell Israel that they must stop acting like a prostitute; she must stop worshiping idols.",
        "id": 9
      }
    ],
    "id": 8
  },
  {
    "t": "q",
    "v": [
      {
        "t": "t",
        "v": "Israel must stop worshiping idols. She must stop acting like a woman who leaves her husband and goes to other men.",
        "id": 11
      }
    ],
    "id": 10
  },
  {
    "t": "q",
    "v": [
      {
        "t": "v",
        "n": 3,
        "v": "If she does not stop,",
        "id": 13
      }
    ],
    "id": 12
  },
  {
    "t": "q",
    "v": [
      {
        "t": "t",
        "v": "I will take her clothes off her and make her naked like she was when she was born.",
        "id": 15
      }
    ],
    "id": 14
  },
  {
    "t": "q",
    "v": [
      {
        "t": "t",
        "v": "I will make her like the barren wilderness—dry and lifeless;",
        "id": 17
      },
      {
        "t": "t",
        "v": "I will make her like a woman dying from thirst in the desert.",
        "id": 18
      }
    ],
    "id": 16
  },
  {
    "t": "q",
    "v": [
      {
        "t": "v",
        "n": 4,
        "v": "I will have no pity on her people, the people of Israel,",
        "id": 20
      }
    ],
    "id": 19
  },
  {
    "t": "q",
    "v": [
      {
        "t": "t",
        "v": "because their nation is like a prostitute.",
        "id": 22
      }
    ],
    "id": 21
  },
  {
    "t": "q",
    "v": [
      {
        "t": "v",
        "n": 5,
        "v": "Israel is like a prostitute;",
        "id": 24
      }
    ],
    "id": 23
  },
  {
    "t": "q",
    "v": [
      {
        "t": "t",
        "v": "she is like a woman who has had these children from doing shameful things with other men.",
        "id": 26
      }
    ],
    "id": 25
  },
  {
    "t": "q",
    "v": [
      {
        "t": "t",
        "v": "Israel decided to hurry after these idols whom she loved, to worship other gods.",
        "id": 28
      }
    ],
    "id": 27
  },
  {
    "t": "q",
    "v": [
      {
        "t": "t",
        "v": "She thought that it was those gods who gave her bread and water.",
        "id": 30
      }
    ],
    "id": 29
  },
  {
    "t": "q",
    "v": [
      {
        "t": "t",
        "v": "She thought that it was those gods who gave her wool, linen, and olive oil, and also wine to drink.",
        "id": 32
      }
    ],
    "id": 31
  },
  {
    "t": "q",
    "v": [
      {
        "t": "v",
        "n": 6,
        "v": "So I will block Israel’s road with thornbushes,",
        "id": 34
      }
    ],
    "id": 33
  },
  {
    "t": "q",
    "v": [
      {
        "t": "t",
        "v": "and I will build a wall around her,",
        "id": 36
      }
    ],
    "id": 35
  },
  {
    "t": "q",
    "v": [
      {
        "t": "t",
        "v": "so that she cannot find the path to take.",
        "id": 38
      }
    ],
    "id": 37
  },
  {
    "t": "q",
    "v": [
      {
        "t": "v",
        "n": 7,
        "v": "Israel will run after her idols",
        "id": 40
      }
    ],
    "id": 39
  },
  {
    "t": "q",
    "v": [
      {
        "t": "t",
        "v": "but she will not find them.",
        "id": 42
      }
    ],
    "id": 41
  },
  {
    "t": "q",
    "v": [
      {
        "t": "t",
        "v": "She will search for her false gods,",
        "id": 44
      }
    ],
    "id": 43
  },
  {
    "t": "q",
    "v": [
      {
        "t": "t",
        "v": "but she will not find them.",
        "id": 46
      }
    ],
    "id": 45
  },
  {
    "t": "q",
    "v": [
      {
        "t": "t",
        "v": "Then, like a prostitute who wants to return to her husband, she will say to me, ‘I will go back to you, the one I loved at first,",
        "id": 48
      }
    ],
    "id": 47
  },
  {
    "t": "q",
    "v": [
      {
        "t": "t",
        "v": "because my life was better with you than it is now.’",
        "id": 50
      }
    ],
    "id": 49
  },
  {
    "t": "q",
    "v": [
      {
        "t": "v",
        "n": 8,
        "v": "The people will say this, because they did not know that it was I, Yahweh, who had given them their grain, new wine, and olive oil.",
        "id": 52
      }
    ],
    "id": 51
  },
  {
    "t": "q",
    "v": [
      {
        "t": "t",
        "v": "It was I who had given them much silver and gold so they would become wealthy.",
        "id": 54
      }
    ],
    "id": 53
  },
  {
    "t": "q",
    "v": [
      {
        "t": "t",
        "v": "But then they made all that gold and silver into objects to use in worshiping the idol Baal.",
        "id": 56
      }
    ],
    "id": 55
  },
  {
    "t": "q",
    "v": [
      {
        "t": "v",
        "n": 9,
        "v": "Therefore I will take away from Israel all the grain I gave them.",
        "id": 58
      }
    ],
    "id": 57
  },
  {
    "t": "q",
    "v": [
      {
        "t": "t",
        "v": "When the wheat is ready for harvest, I will keep them from getting it.",
        "id": 60
      }
    ],
    "id": 59
  },
  {
    "t": "q",
    "v": [
      {
        "t": "t",
        "v": "The new wine that I gave them, I will take it away.",
        "id": 62
      }
    ],
    "id": 61
  },
  {
    "t": "q",
    "v": [
      {
        "t": "t",
        "v": "I will take away from them all the wool and linen I gave them to make clothes for themselves,",
        "id": 64
      }
    ],
    "id": 63
  },
  {
    "t": "q",
    "v": [
      {
        "t": "t",
        "v": "the clothes that covered their nakedness.",
        "id": 66
      }
    ],
    "id": 65
  },
  {
    "t": "q",
    "v": [
      {
        "t": "v",
        "n": 10,
        "v": "I will treat Israel as a man treats his wife when he finds her with other men.",
        "id": 68
      }
    ],
    "id": 67
  },
  {
    "t": "q",
    "v": [
      {
        "t": "t",
        "v": "I will strip her naked in front of her lovers.",
        "id": 70
      }
    ],
    "id": 69
  },
  {
    "t": "q",
    "v": [
      {
        "t": "t",
        "v": "No one will be able rescue her from what I will do to her.",
        "id": 72
      }
    ],
    "id": 71
  },
  {
    "t": "q",
    "v": [
      {
        "t": "v",
        "n": 11,
        "v": "I will make the people in Israel stop holding their celebrations;",
        "id": 74
      }
    ],
    "id": 73
  },
  {
    "t": "q",
    "v": [
      {
        "t": "t",
        "v": "they will stop holding their festivals every year.",
        "id": 76
      }
    ],
    "id": 75
  },
  {
    "t": "q",
    "v": [
      {
        "t": "t",
        "v": "They will no longer celebrate the beginning of every month.",
        "id": 78
      }
    ],
    "id": 77
  },
  {
    "t": "q",
    "v": [
      {
        "t": "t",
        "v": "They will no longer celebrate the Sabbath days.",
        "id": 80
      }
    ],
    "id": 79
  },
  {
    "t": "q",
    "v": [
      {
        "t": "t",
        "v": "They will no longer be able to hold the festivals scheduled throughout the year.",
        "id": 82
      }
    ],
    "id": 81
  },
  {
    "t": "q",
    "v": [
      {
        "t": "v",
        "n": 12,
        "v": "I will destroy all of Israel’s grapevines and fig trees.",
        "id": 84
      }
    ],
    "id": 83
  },
  {
    "t": "q",
    "v": [
      {
        "t": "t",
        "v": "This is because Israel is like a woman who says, ‘These were the things that my lovers gave me in payment.’",
        "id": 86
      }
    ],
    "id": 85
  },
  {
    "t": "q",
    "v": [
      {
        "t": "t",
        "v": "I, Yahweh, will turn those places into a forest, a thicket in which no vines can grow,",
        "id": 88
      }
    ],
    "id": 87
  },
  {
    "t": "q",
    "v": [
      {
        "t": "t",
        "v": "and where wild animals will devour any fruit that grows there.’",
        "id": 90
      }
    ],
    "id": 89
  },
  {
    "t": "q",
    "v": [
      {
        "t": "v",
        "n": 13,
        "v": "I will punish this woman named Israel for all the times that she burned incense to worship the Baal idols.",
        "id": 92
      }
    ],
    "id": 91
  },
  {
    "t": "q",
    "v": [
      {
        "t": "t",
        "v": "She decorated herself with rings and jewelry, as a prostitute would adorn herself for her lovers.",
        "id": 94
      }
    ],
    "id": 93
  },
  {
    "t": "q",
    "v": [
      {
        "t": "t",
        "v": "She used to follow her lovers—like Israel has gone after the Baals—those false gods that she worshiped.",
        "id": 96
      }
    ],
    "id": 95
  },
  {
    "t": "q",
    "v": [
      {
        "t": "t",
        "v": "And she forgot about me.” This is what Yahweh says.",
        "id": 98
      }
    ],
    "id": 97
  },
  {
    "t": "q",
    "v": [
      {
        "t": "v",
        "n": 14,
        "v": "“I will lead her into the wilderness and tell her that I love her.",
        "id": 100
      }
    ],
    "id": 99
  },
  {
    "t": "q",
    "v": [
      {
        "t": "t",
        "v": "I will persuade her to love me again.",
        "id": 102
      },
      {
        "t": "v",
        "n": 15,
        "v": "I will give her vineyards back to her once more,",
        "id": 103
      }
    ],
    "id": 101
  },
  {
    "t": "q",
    "v": [
      {
        "t": "t",
        "v": "and in the Valley of Achor I will cause her to hope once more.",
        "id": 105
      }
    ],
    "id": 104
  },
  {
    "t": "q",
    "v": [
      {
        "t": "t",
        "v": "She will answer me with love and delight, as it was back in the first days when we first loved each other—",
        "id": 107
      }
    ],
    "id": 106
  },
  {
    "t": "q",
    "v": [
      {
        "t": "t",
        "v": "when I set her free, and she came up out of Egypt.",
        "id": 109
      }
    ],
    "id": 108
  },
  {
    "t": "q",
    "v": [
      {
        "t": "v",
        "n": 16,
        "v": "At that time,",
        "id": 111
      }
    ],
    "id": 110
  },
  {
    "t": "q",
    "v": [
      {
        "t": "t",
        "v": "Israel will call me, ‘My Husband,’ as a woman would say to her human husband.",
        "id": 113
      }
    ],
    "id": 112
  },
  {
    "t": "q",
    "v": [
      {
        "t": "t",
        "v": "She will no longer call out to a god, ‘My Baal,’ but she will call out to me as ‘My Husband.’",
        "id": 115
      }
    ],
    "id": 114
  },
  {
    "t": "q",
    "v": [
      {
        "t": "v",
        "n": 17,
        "v": "I will not allow Israel to speak the names of the images of Baal that she used to worship.",
        "id": 117
      }
    ],
    "id": 116
  },
  {
    "t": "q",
    "v": [
      {
        "t": "t",
        "v": "My people will forget the names of those Baals and their idols, and my people Israel will never worship them again.",
        "id": 119
      }
    ],
    "id": 118
  },
  {
    "t": "q",
    "v": [
      {
        "t": "v",
        "n": 18,
        "v": "At that time I will make a covenant for them:",
        "id": 121
      }
    ],
    "id": 120
  },
  {
    "t": "q",
    "v": [
      {
        "t": "t",
        "v": "it will be with all the wild animals and birds,",
        "id": 123
      }
    ],
    "id": 122
  },
  {
    "t": "q",
    "v": [
      {
        "t": "t",
        "v": "and even with the little animals that crawl along the ground.",
        "id": 125
      }
    ],
    "id": 124
  },
  {
    "t": "q",
    "v": [
      {
        "t": "t",
        "v": "They will never harm my people again.",
        "id": 127
      }
    ],
    "id": 126
  },
  {
    "t": "q",
    "v": [
      {
        "t": "t",
        "v": "I will promise to remove all the weapons that are used for fighting battles,",
        "id": 129
      }
    ],
    "id": 128
  },
  {
    "t": "q",
    "v": [
      {
        "t": "t",
        "v": "the bows and arrows, and the swords, and every war, I will take them all away and destroy all of them.",
        "id": 131
      }
    ],
    "id": 130
  },
  {
    "t": "q",
    "v": [
      {
        "t": "t",
        "v": "And I will let all of my people rest in peace;",
        "id": 133
      }
    ],
    "id": 132
  },
  {
    "t": "q",
    "v": [
      {
        "t": "t",
        "v": "they will be not be afraid anymore.",
        "id": 135
      }
    ],
    "id": 134
  },
  {
    "t": "q",
    "v": [
      {
        "t": "v",
        "n": 19,
        "v": "You will be like my wife forever, Israel.",
        "id": 137
      }
    ],
    "id": 136
  },
  {
    "t": "q",
    "v": [
      {
        "t": "t",
        "v": "I will promise myself to you, by doing what is right, and by loving what is just.",
        "id": 139
      }
    ],
    "id": 138
  },
  {
    "t": "q",
    "v": [
      {
        "t": "t",
        "v": "I promise to love you and to show you kindness even when you do not deserve it.",
        "id": 141
      }
    ],
    "id": 140
  },
  {
    "t": "q",
    "v": [
      {
        "t": "v",
        "n": 20,
        "v": "I will keep my promise to you, Israel. I will never lie to you;",
        "id": 143
      }
    ],
    "id": 142
  },
  {
    "t": "q",
    "v": [
      {
        "t": "t",
        "v": "and you will come to know me—my name is Yahweh.",
        "id": 145
      }
    ],
    "id": 144
  },
  {
    "t": "q",
    "v": [
      {
        "t": "v",
        "n": 21,
        "v": "At that time,",
        "id": 147
      }
    ],
    "id": 146
  },
  {
    "t": "q",
    "v": [
      {
        "t": "t",
        "v": "I will help you,” says Yahweh.",
        "id": 149
      }
    ],
    "id": 148
  },
  {
    "t": "q",
    "v": [
      {
        "t": "t",
        "v": "“I will give a command to the sky,",
        "id": 151
      }
    ],
    "id": 150
  },
  {
    "t": "q",
    "v": [
      {
        "t": "t",
        "v": "and the sky will pour out rain onto the ground.",
        "id": 153
      }
    ],
    "id": 152
  },
  {
    "t": "q",
    "v": [
      {
        "t": "v",
        "n": 22,
        "v": "And the ground will provide grain, new wine and olive trees, and they will grow for the people of Israel.",
        "id": 155
      }
    ],
    "id": 154
  },
  {
    "t": "q",
    "v": [
      {
        "t": "v",
        "n": 23,
        "v": "At that time, I will take care of the Israelite people",
        "id": 157
      }
    ],
    "id": 156
  },
  {
    "t": "q",
    "v": [
      {
        "t": "t",
        "v": "as a farmer plants his own land and takes care of his crops.",
        "id": 159
      }
    ],
    "id": 158
  },
  {
    "t": "q",
    "v": [
      {
        "t": "t",
        "v": "I will show my love to those people whom I called ‘Not my People’.",
        "id": 161
      }
    ],
    "id": 160
  },
  {
    "t": "q",
    "v": [
      {
        "t": "t",
        "v": "And those whom I called ‘Not my People’,",
        "id": 163
      }
    ],
    "id": 162
  },
  {
    "t": "q",
    "v": [
      {
        "t": "t",
        "v": "I will now call by a new name: ‘You are my People’.",
        "id": 165
      }
    ],
    "id": 164
  },
  {
    "t": "q",
    "v": [
      {
        "t": "t",
        "v": "They will say to me, ‘You are our God.’”",
        "id": 167
      }
    ],
    "id": 166
  }
]