{
  "chapter": {
    "children": [
      {
        "tag": "p",
        "children": [
          {
            "tag": "v",
            "num": "1",
            "text": "\"It is true that there are places where men dig to find silver,"
          },
          {
            "tag": "q2",
            "text": "and there are places where people refine gold that they have dug."
          },
          {
            "tag": "v",
            "num": "2",
            "text": "People dig iron ore out of the ground,"
          },
          {
            "tag": "q2",
            "text": "and they also smelt copper."
          },
          {
            "tag": "v",
            "num": "3",
            "text": "Men use lamps while they work far down under the ground"
          },
          {
            "tag": "q2",
            "text": "to search for the ore inside the mines"
          },
          {
            "tag": "q2",
            "text": "where it is very dark."
          },
          {
            "tag": "v",
            "num": "4",
            "text": "They dig shafts in places that are far from where people live,"
          },
          {
            "tag": "q2",
            "text": "where travelers do not go."
          },
          {
            "tag": "q1",
            "text": "They work far away from other people,"
          },
          {
            "tag": "q2",
            "text": "swinging back and forth on ropes as they descend into the mine shafts."
          },
          {
            "tag": "v",
            "num": "5",
            "text": "Food grows on the surface of the ground,"
          },
          {
            "tag": "q2",
            "text": "but down under the ground, where there is no food, the miners make fires to break apart the rocks."
          },
          {
            "tag": "v",
            "num": "6",
            "text": "The stones that are dug from under the ground contain sapphires,"
          },
          {
            "tag": "q2",
            "text": "and the dirt contains bits of gold."
          },
          {
            "tag": "v",
            "num": "7",
            "text": "Some birds have very good eyes,"
          },
          {
            "tag": "q1",
            "text": "but even hawks do not know where the mines are,"
          },
          {
            "tag": "q2",
            "text": "and falcons have not seen those places."
          },
          {
            "tag": "v",
            "num": "8",
            "text": "Lions or other proud wild animals have never gone to those places."
          },
          {
            "tag": "v",
            "num": "9",
            "text": "Miners dig very hard rock;"
          },
          {
            "tag": "q2",
            "text": "it is as though they turned the mountains upside down to get the ore."
          },
          {
            "tag": "v",
            "num": "10",
            "text": "They cut tunnels through the rocks,"
          },
          {
            "tag": "q2",
            "text": "and they find precious things."
          },
          {
            "tag": "v",
            "num": "11",
            "text": "They dam up small streams to stop the water from flowing,"
          },
          {
            "tag": "q2",
            "text": "and they bring up into the light things that are hidden in the ground and in the streams."
          },
          {
            "tag": "v",
            "num": "12",
            "text": "But wisdom: Where can people find that?"
          },
          {
            "tag": "q2",
            "text": "Where can we find out how to truly understand things?"
          },
          {
            "tag": "v",
            "num": "13",
            "text": "Humans do not know what wisdom is truly worth;"
          },
          {
            "tag": "q2",
            "text": "no one can find it here on this earth where they are living."
          },
          {
            "tag": "v",
            "num": "14",
            "text": "It is as though the water that is under the earth and water that is in the seas said,"
          },
          {
            "tag": "q2",
            "text": "'I do not have it!'"
          },
          {
            "tag": "v",
            "num": "15",
            "text": "People cannot buy wisdom"
          },
          {
            "tag": "q2",
            "text": "by paying for it with silver or gold."
          },
          {
            "tag": "v",
            "num": "16",
            "text": "Wisdom is worth much more than fine gold from the land of Ophir,"
          },
          {
            "tag": "q2",
            "text": "much more than very valuable stones."
          },
          {
            "tag": "v",
            "num": "17",
            "text": "It is worth much more than gold or beautiful quartz;"
          },
          {
            "tag": "q2",
            "text": "wisdom is more expensive than the finest jewels, and it is worth more than a vase made with pure gold."
          },
          {
            "tag": "v",
            "num": "18",
            "text": "Wisdom is worth more than coral or crystal quartz;"
          },
          {
            "tag": "q2",
            "text": "the price of wisdom is higher than the price of rubies."
          },
          {
            "tag": "v",
            "num": "19",
            "text": "The prices of topaz from Ethiopia and of pure gold"
          },
          {
            "tag": "q2",
            "text": "are lower than the value of wisdom."
          },
          {
            "tag": "v",
            "num": "20",
            "text": "So from where does wisdom come?"
          },
          {
            "tag": "q2",
            "text": "Where can we find out how to truly understand things?"
          },
          {
            "tag": "v",
            "num": "21",
            "text": "No living humans can see it;"
          },
          {
            "tag": "q2",
            "text": "and birds cannot see it while they are up in the sky."
          },
          {
            "tag": "v",
            "num": "22",
            "text": "It is as though the places where people go after they die said,"
          },
          {
            "tag": "q2",
            "text": "'We have only heard rumors about where to find wisdom.'"
          },
          {
            "tag": "v",
            "num": "23",
            "text": "God is the only one who knows how to find wisdom;"
          },
          {
            "tag": "q2",
            "text": "he knows where it is"
          },
          {
            "tag": "v",
            "num": "24",
            "text": "because he can see things even in the most remote places on the earth;"
          },
          {
            "tag": "q2",
            "text": "he can see everything that is below the sky."
          },
          {
            "tag": "v",
            "num": "25",
            "text": "He decided how strongly the winds should blow,"
          },
          {
            "tag": "q2",
            "text": "and how much rain should be in the clouds."
          },
          {
            "tag": "v",
            "num": "26",
            "text": "He decided where rain should fall,"
          },
          {
            "tag": "q2",
            "text": "and what path lightning should take from the clouds down to the ground."
          },
          {
            "tag": "v",
            "num": "27",
            "text": "At that time he saw wisdom and decided that it is very valuable."
          },
          {
            "tag": "q2",
            "text": "He examined it and approved it."
          },
          {
            "tag": "v",
            "num": "28",
            "text": "And then he said to human beings, 'Listen! If you have much respect for me, you will be able to become wise;"
          },
          {
            "tag": "q2",
            "text": "to truly understand everything, you must first turn away from doing what is evil.'\""
          }
        ],
        "auto": true
      }
    ],
    "num": 28
  },
  "id": "JOB unfoldingWord® Simplified Text",
  "usfm": ".0",
  "ide": "UTF-8",
  "h": "Job"
}